setup.py
musictools/__init__.py
musictools/custom_exceptions.py
musictools/musictools.py
musictools.egg-info/PKG-INFO
musictools.egg-info/SOURCES.txt
musictools.egg-info/dependency_links.txt
musictools.egg-info/requires.txt
musictools.egg-info/top_level.txt
tests/__init__.py
tests/musictools_tests.py