Metadata-Version: 1.0
Name: musictools
Version: 2.2.0
Summary: Lets you repair your music files by adding metadata and album art
Home-page: https://github.com/lakshaykalbhor/musictools
Author: Lakshay Kalbhor
Author-email: lakshaykalbhor@gmail.com
License: MIT
Platform: UNKNOWN
